<?xml version="1.0"?>
<fsimage>
    <version>
        <layoutVersion>-63</layoutVersion>
        <onDiskVersion>1</onDiskVersion>
        <oivRevision>17e75c2a11685af3e043aa5e604dc831e5b14674</oivRevision>
    </version>
    <NameSection>
        <namespaceId>117574680</namespaceId>
        <genstampV1>1000</genstampV1>
        <genstampV2>1003</genstampV2>
        <genstampV1Limit>0</genstampV1Limit>
        <lastAllocatedBlockId>1073741827</lastAllocatedBlockId>
        <txid>26</txid>
    </NameSection>
    <INodeSection>
        <lastInodeId>16391</lastInodeId>
        <numInodes>4</numInodes>
        <inode>
            <id>16385</id>
            <type>DIRECTORY</type>
            <name></name>
            <mtime>1536216768921</mtime>
            <permission>root:supergroup:0755</permission>
            <nsquota>9223372036854775807</nsquota>
            <dsquota>-1</dsquota>
        </inode>
        <inode>
            <id>16386</id>
            <type>DIRECTORY</type>
            <name>usr</name>
            <mtime>1536216768923</mtime>
            <permission>root:supergroup:0755</permission>
            <nsquota>-1</nsquota>
            <dsquota>-1</dsquota>
        </inode>
        <inode>
            <id>16387</id>
            <type>DIRECTORY</type>
            <name>hadoop</name>
            <mtime>1536217618368</mtime>
            <permission>root:supergroup:0755</permission>
            <nsquota>-1</nsquota>
            <dsquota>-1</dsquota>
        </inode>
        <inode>
            <id>16391</id>
            <type>FILE</type>
            <name>a2.txt</name>
            <replication>2</replication>
            <mtime>1536217618368</mtime>
            <atime>1536217618368</atime>
            <preferredBlockSize>64</preferredBlockSize>
            <permission>root:supergroup:0644</permission>
            <storagePolicyId>0</storagePolicyId>
            <file-under-construction>
                <clientName>DFSClient_NONMAPREDUCE_2035625156_1</clientName>
                <clientMachine>192.168.1.1</clientMachine>
            </file-under-construction>
        </inode>
    </INodeSection>
    <INodeReferenceSection></INodeReferenceSection>
    <SnapshotSection>
        <snapshotCounter>0</snapshotCounter>
        <numSnapshots>0</numSnapshots>
    </SnapshotSection>
    <INodeDirectorySection>
        <directory>
            <parent>16385</parent>
            <child>16386</child>
        </directory>
        <directory>
            <parent>16386</parent>
            <child>16387</child>
        </directory>
        <directory>
            <parent>16387</parent>
            <child>16391</child>
        </directory>
    </INodeDirectorySection>
    <FileUnderConstructionSection>
        <inode>
            <id>16391</id>
            <path>/usr/hadoop/a2.txt</path>
        </inode>
    </FileUnderConstructionSection>
    <SecretManagerSection>
        <currentId>0</currentId>
        <tokenSequenceNumber>0</tokenSequenceNumber>
        <numDelegationKeys>0</numDelegationKeys>
        <numTokens>0</numTokens>
    </SecretManagerSection>
    <CacheManagerSection>
        <nextDirectiveId>1</nextDirectiveId>
        <numDirectives>0</numDirectives>
        <numPools>0</numPools>
    </CacheManagerSection>
</fsimage>
